{"city":"Omaha","state":"Nebraska","state_abbr":"NE","slug":"omaha-ne","population":478000,"region":"Midwest","col_index":82,"last_updated":"2026-03-24","gas":{"current":3.367,"diesel_current":3.82,"national_current":3.45,"history":[{"date":"2021-04","price":3.155,"national":3.11},{"date":"2021-05","price":3.072,"national":3.097},{"date":"2021-06","price":3.039,"national":3.06},{"date":"2021-07","price":2.97,"national":3.01},{"date":"2021-08","price":2.996,"national":2.96},{"date":"2021-09","price":2.877,"national":2.923},{"date":"2021-10","price":2.912,"national":2.91},{"date":"2021-11","price":2.958,"national":2.923},{"date":"2021-12","price":2.939,"national":2.96},{"date":"2022-01","price":3.956,"national":3.95},{"date":"2022-02","price":4.005,"national":4},{"date":"2022-03","price":4.079,"national":4.037},{"date":"2022-04","price":4.089,"national":4.05},{"date":"2022-05","price":4.07,"national":4.037},{"date":"2022-06","price":4.04,"national":4},{"date":"2022-07","price":3.944,"national":3.95},{"date":"2022-08","price":3.949,"national":3.9},{"date":"2022-09","price":3.907,"national":3.863},{"date":"2022-10","price":3.885,"national":3.85},{"date":"2022-11","price":3.894,"national":3.863},{"date":"2022-12","price":3.894,"national":3.9},{"date":"2023-01","price":3.558,"national":3.53},{"date":"2023-02","price":3.559,"national":3.58},{"date":"2023-03","price":3.616,"national":3.617},{"date":"2023-04","price":3.664,"national":3.63},{"date":"2023-05","price":3.629,"national":3.617},{"date":"2023-06","price":3.549,"national":3.58},{"date":"2023-07","price":3.574,"national":3.53},{"date":"2023-08","price":3.48,"national":3.48},{"date":"2023-09","price":3.487,"national":3.443},{"date":"2023-10","price":3.389,"national":3.43},{"date":"2023-11","price":3.46,"national":3.443},{"date":"2023-12","price":3.439,"national":3.48},{"date":"2024-01","price":3.357,"national":3.31},{"date":"2024-02","price":3.355,"national":3.36},{"date":"2024-03","price":3.356,"national":3.397},{"date":"2024-04","price":3.361,"national":3.41},{"date":"2024-05","price":3.375,"national":3.397},{"date":"2024-06","price":3.327,"national":3.36},{"date":"2024-07","price":3.356,"national":3.31},{"date":"2024-08","price":3.259,"national":3.26},{"date":"2024-09","price":3.195,"national":3.223},{"date":"2024-10","price":3.167,"national":3.21},{"date":"2024-11","price":3.204,"national":3.223},{"date":"2024-12","price":3.256,"national":3.26},{"date":"2025-01","price":3.249,"national":3.2},{"date":"2025-02","price":3.211,"national":3.25},{"date":"2025-03","price":3.299,"national":3.287},{"date":"2025-04","price":3.257,"national":3.3},{"date":"2025-05","price":3.264,"national":3.287},{"date":"2025-06","price":3.253,"national":3.25},{"date":"2025-07","price":3.152,"national":3.2},{"date":"2025-08","price":3.106,"national":3.15},{"date":"2025-09","price":3.139,"national":3.113},{"date":"2025-10","price":3.138,"national":3.1},{"date":"2025-11","price":3.072,"national":3.113},{"date":"2025-12","price":3.124,"national":3.15},{"date":"2026-01","price":3.483,"national":3.45},{"date":"2026-02","price":3.519,"national":3.5},{"date":"2026-03","price":3.503,"national":3.537}]},"rent":{"avg_all":1394,"avg_1br":1143,"avg_2br":1645,"avg_3br":1559.25,"national_avg":1900,"median_home_price":223450,"history":[{"date":"2021-04","avg":1454.15,"onebed":1163.32,"national":1430},{"date":"2021-05","avg":1445.81,"onebed":1156.64,"national":1430},{"date":"2021-06","avg":1473.57,"onebed":1178.85,"national":1430},{"date":"2021-07","avg":1440.31,"onebed":1152.24,"national":1430},{"date":"2021-08","avg":1455.72,"onebed":1164.58,"national":1430},{"date":"2021-09","avg":1442.6,"onebed":1154.07,"national":1430},{"date":"2021-10","avg":1445.59,"onebed":1156.47,"national":1430},{"date":"2021-11","avg":1435.06,"onebed":1148.05,"national":1430},{"date":"2021-12","avg":1459.15,"onebed":1167.32,"national":1430},{"date":"2022-01","avg":1222.8,"onebed":953.79,"national":1640},{"date":"2022-02","avg":1649.89,"onebed":1319.91,"national":1640},{"date":"2022-03","avg":1658.58,"onebed":1326.87,"national":1640},{"date":"2022-04","avg":1653.53,"onebed":1322.82,"national":1640},{"date":"2022-05","avg":1657.99,"onebed":1326.38,"national":1640},{"date":"2022-06","avg":1639.53,"onebed":1311.62,"national":1640},{"date":"2022-07","avg":1660.25,"onebed":1328.2,"national":1640},{"date":"2022-08","avg":1652.88,"onebed":1322.31,"national":1640},{"date":"2022-09","avg":1648.73,"onebed":1318.98,"national":1640},{"date":"2022-10","avg":1647.31,"onebed":1317.85,"national":1640},{"date":"2022-11","avg":1677.56,"onebed":1342.05,"national":1640},{"date":"2022-12","avg":1679.69,"onebed":1343.74,"national":1640},{"date":"2023-01","avg":1302.81,"onebed":1016.19,"national":1820},{"date":"2023-02","avg":1868.76,"onebed":1495.01,"national":1820},{"date":"2023-03","avg":1825.36,"onebed":1460.29,"national":1820},{"date":"2023-04","avg":1838.86,"onebed":1471.08,"national":1820},{"date":"2023-05","avg":1840.4,"onebed":1472.32,"national":1820},{"date":"2023-06","avg":1843.47,"onebed":1474.78,"national":1820},{"date":"2023-07","avg":1860.25,"onebed":1488.2,"national":1820},{"date":"2023-08","avg":1852.7,"onebed":1482.16,"national":1820},{"date":"2023-09","avg":1850.86,"onebed":1480.68,"national":1820},{"date":"2023-10","avg":1862.04,"onebed":1489.64,"national":1820},{"date":"2023-11","avg":1851.44,"onebed":1481.16,"national":1820},{"date":"2023-12","avg":1854.02,"onebed":1483.22,"national":1820},{"date":"2024-01","avg":1353.39,"onebed":1055.65,"national":1890},{"date":"2024-02","avg":1922.4,"onebed":1537.92,"national":1890},{"date":"2024-03","avg":1931.96,"onebed":1545.57,"national":1890},{"date":"2024-04","avg":1902.17,"onebed":1521.74,"national":1890},{"date":"2024-05","avg":1895.22,"onebed":1516.18,"national":1890},{"date":"2024-06","avg":1930.73,"onebed":1544.58,"national":1890},{"date":"2024-07","avg":1899.34,"onebed":1519.47,"national":1890},{"date":"2024-08","avg":1938.07,"onebed":1550.46,"national":1890},{"date":"2024-09","avg":1905.44,"onebed":1524.36,"national":1890},{"date":"2024-10","avg":1937.5,"onebed":1550.01,"national":1890},{"date":"2024-11","avg":1905.4,"onebed":1524.32,"national":1890},{"date":"2024-12","avg":1920.41,"onebed":1536.33,"national":1890},{"date":"2025-01","avg":1935.44,"onebed":1548.36,"national":1900},{"date":"2025-02","avg":1917.56,"onebed":1534.05,"national":1900},{"date":"2025-03","avg":1919.0,"onebed":1535.21,"national":1900},{"date":"2025-04","avg":1903.42,"onebed":1522.73,"national":1900},{"date":"2025-05","avg":1903.06,"onebed":1522.45,"national":1900},{"date":"2025-06","avg":1915.1,"onebed":1532.08,"national":1900},{"date":"2025-07","avg":1948.95,"onebed":1559.16,"national":1900},{"date":"2025-08","avg":1937.87,"onebed":1550.3,"national":1900},{"date":"2025-09","avg":1905.91,"onebed":1524.73,"national":1900},{"date":"2025-10","avg":1927.48,"onebed":1541.98,"national":1900},{"date":"2025-11","avg":1904.13,"onebed":1523.3,"national":1900},{"date":"2025-12","avg":1945.25,"onebed":1556.2,"national":1900},{"date":"2026-01","avg":1947.72,"onebed":1558.18,"national":1900},{"date":"2026-02","avg":1931.25,"onebed":1545.0,"national":1900},{"date":"2026-03","avg":1394.0,"onebed":1087.32,"national":1900}],"baseline_2022":1121,"yoy_change_pct":3.7,"source":"Zillow ZORI (Metro, Feb 2026)"},"groceries":{"items":[{"name":"Eggs (dozen)","slug":"eggs","unit":"dozen","current":2.5,"history":[{"date":"2022","price":1.72},{"date":"2023","price":1.99},{"date":"2024","price":2.52},{"date":"2025","price":3.77},{"date":"2026","price":2.07}],"change_from_2022":29.6,"note":"Bird flu volatility","source":"BLS/FRED APU0000708111","price_2022":1.929},{"name":"Milk (gallon)","slug":"milk","unit":"gallon","current":4.026,"history":[{"date":"2022","price":3.25},{"date":"2023","price":3.51},{"date":"2024","price":3.51},{"date":"2025","price":3.54},{"date":"2026","price":3.54}],"change_from_2022":6.3,"source":"BLS/FRED APU0000709112","price_2022":3.787},{"name":"Ground Beef (lb)","slug":"ground-beef","unit":"lb","current":5.11,"history":[{"date":"2022","price":3.78},{"date":"2023","price":4.64},{"date":"2024","price":4.82},{"date":"2025","price":5.06},{"date":"2026","price":5.11}],"change_from_2022":0.352},{"name":"Bread (loaf)","slug":"bread","unit":"loaf","current":1.85,"history":[{"date":"2022","price":2.08},{"date":"2023","price":2.81},{"date":"2024","price":3.03},{"date":"2025","price":3.28},{"date":"2026","price":3.35}],"change_from_2022":19,"source":"BLS/FRED APU0000702111","price_2022":1.555},{"name":"Chicken Breast (lb)","slug":"chicken","unit":"lb","current":2.049,"history":[{"date":"2022","price":3.5},{"date":"2023","price":3.71},{"date":"2024","price":3.74},{"date":"2025","price":3.82},{"date":"2026","price":3.9}],"change_from_2022":26.3,"source":"BLS/FRED APU0000706111","price_2022":1.622},{"name":"Butter (lb)","slug":"butter","unit":"lb","current":5.06,"history":[{"date":"2022","price":4.01},{"date":"2023","price":4.4},{"date":"2024","price":4.67},{"date":"2025","price":4.91},{"date":"2026","price":5.06}],"change_from_2022":0.262},{"name":"Bacon (lb)","slug":"bacon","unit":"lb","current":7.46,"history":[{"date":"2022","price":6.09},{"date":"2023","price":6.71},{"date":"2024","price":7.18},{"date":"2025","price":7.39},{"date":"2026","price":7.46}],"change_from_2022":0.225},{"name":"Cheddar Cheese (lb)","slug":"cheddar-cheese","unit":"lb","current":6.85,"history":[{"date":"2022","price":5.54},{"date":"2023","price":6.15},{"date":"2024","price":6.4},{"date":"2025","price":6.72},{"date":"2026","price":6.85}],"change_from_2022":0.236},{"name":"Pasta (lb)","slug":"pasta","unit":"lb","current":1.86,"history":[{"date":"2022","price":1.34},{"date":"2023","price":1.67},{"date":"2024","price":1.77},{"date":"2025","price":1.86},{"date":"2026","price":1.86}],"change_from_2022":0.388},{"name":"Rice (5 lb)","slug":"rice","unit":"5 lb bag","current":5.05,"history":[{"date":"2022","price":3.98},{"date":"2023","price":4.62},{"date":"2024","price":4.9},{"date":"2025","price":5},{"date":"2026","price":5.05}],"change_from_2022":0.269},{"name":"Coffee (12 oz)","slug":"coffee","unit":"12 oz","current":10.17,"history":[{"date":"2022","price":7.57},{"date":"2023","price":9.17},{"date":"2024","price":9.8},{"date":"2025","price":10.08},{"date":"2026","price":10.17}],"change_from_2022":0.343},{"name":"Orange Juice (64 oz)","slug":"orange-juice","unit":"64 oz","current":5.3,"history":[{"date":"2022","price":3.67},{"date":"2023","price":4.33},{"date":"2024","price":4.76},{"date":"2025","price":5},{"date":"2026","price":5.3}],"change_from_2022":0.444,"note":"Citrus shortage"},{"name":"Potatoes (5 lb)","slug":"potatoes","unit":"5 lb bag","current":4.38,"history":[{"date":"2022","price":3.82},{"date":"2023","price":3.97},{"date":"2024","price":4.17},{"date":"2025","price":4.25},{"date":"2026","price":4.38}],"change_from_2022":0.147},{"name":"Apples (3 lb)","slug":"apples","unit":"3 lb bag","current":4.69,"history":[{"date":"2022","price":4.09},{"date":"2023","price":4.34},{"date":"2024","price":4.56},{"date":"2025","price":4.6},{"date":"2026","price":4.69}],"change_from_2022":0.147},{"name":"Tomatoes (lb)","slug":"tomatoes","unit":"lb","current":2.6,"history":[{"date":"2022","price":2.02},{"date":"2023","price":2.29},{"date":"2024","price":2.4},{"date":"2025","price":2.55},{"date":"2026","price":2.6}],"change_from_2022":0.287},{"name":"Lettuce (head)","slug":"lettuce","unit":"head","current":2.24,"history":[{"date":"2022","price":1.69},{"date":"2023","price":1.88},{"date":"2024","price":2.03},{"date":"2025","price":2.13},{"date":"2026","price":2.24}],"change_from_2022":0.325},{"name":"Cooking Oil (48 oz)","slug":"cooking-oil","unit":"48 oz","current":7.46,"history":[{"date":"2022","price":5.1},{"date":"2023","price":6.38},{"date":"2024","price":6.89},{"date":"2025","price":7.24},{"date":"2026","price":7.46}],"change_from_2022":0.463},{"name":"Yogurt (32 oz)","slug":"yogurt","unit":"32 oz","current":4.6,"history":[{"date":"2022","price":3.94},{"date":"2023","price":4.26},{"date":"2024","price":4.47},{"date":"2025","price":4.56},{"date":"2026","price":4.6}],"change_from_2022":0.168},{"name":"Cereal (family size)","slug":"cereal","unit":"box","current":5.75,"history":[{"date":"2022","price":4.45},{"date":"2023","price":5.07},{"date":"2024","price":5.48},{"date":"2025","price":5.64},{"date":"2026","price":5.75}],"change_from_2022":0.292},{"name":"Frozen Pizza","slug":"frozen-pizza","unit":"each","current":8.3,"history":[{"date":"2022","price":5.81},{"date":"2023","price":6.97},{"date":"2024","price":7.45},{"date":"2025","price":7.9},{"date":"2026","price":8.3}],"change_from_2022":0.429}],"inflation_rate":{"current_yoy":2.58,"history":[{"year":"2022","rate":10.45},{"year":"2023","rate":4.32},{"year":"2024","rate":2.33},{"year":"2025","rate":2.98},{"year":"2026","rate":2.78}],"source":"BLS CPI Food at Home (CUSR0000SAF11)"}},"dining":{"fast_food_avg":11.75,"casual_dining_avg":19.99,"coffee_avg":5.07,"monthly_household_spend":298.2,"restaurant_inflation_yoy":5.13,"chains":[{"name":"McDonald's","price_2022":6.22,"price_current":10.04},{"name":"Wendy's","price_2022":7.03,"price_current":10.84},{"name":"Chipotle","price_2022":7.53,"price_current":11.24},{"name":"Starbucks","price_2022":3.65,"price_current":5.07}]},"utilities":{"electricity_kwh":0.14,"natural_gas_therm":1.09,"internet_monthly":63.24,"phone_monthly":90.23,"national_electricity":0.16},"transportation":{"car_insurance_monthly":109.06,"used_car_avg":17498.8,"gas_per_month_avg":186.65},"healthcare":{"doctor_visit":143.58,"prescription_generic":19.98,"dental_cleaning":102.95},"personal":{"haircut_mens":15.25,"gym_membership":29.6,"movie_ticket":10.79},"data_sources":{"groceries":"BLS/FRED APU series \u2014 national avg prices","gas":"AAA Gas Prices \u2014 state-level avg"},"electricity":{"cents_per_kwh":11.4,"monthly_avg_bill":102.6,"national_avg_cents":16.2,"national_avg_bill":145.8,"source":"EIA Residential Electric Power (2025)"},"car_insurance":{"annual_avg":1780,"monthly_avg":148.33,"national_avg_annual":2150,"source":"Bankrate/NAIC state avg full coverage (2025)"}}